llm_x/__about__.py
llm_x/__init__.py
llm_x/cli.py
llm_x/pipeline.py
llm_x/print.py
llm_x/py.typed
llm_x/estimation/__init__.py
llm_x/estimation/kv_cache.py
llm_x/estimation/memory.py
llm_x/estimation/tensor_synthesizer.py
llm_x/hub/__init__.py
llm_x/hub/hf_client.py
llm_x/hub/safetensors_metadata.py
llm_x/hub/sentence_transformers.py
llm_x/utils/__init__.py
llm_x/utils/hardware.py
llm_x/utils/types.py
llm_x_py-0.1.5.dist-info/licenses/LICENSE
llm_x_py-0.1.5.dist-info/METADATA
llm_x_py-0.1.5.dist-info/WHEEL
llm_x_py-0.1.5.dist-info/entry_points.txt
llm_x_py-0.1.5.dist-info/top_level.txt
llm_x_py-0.1.5.dist-info/RECORD
