Metadata-Version: 2.4
Name: llm-x-py
Version: 0.1.5
Summary: Python library for precise, hardware-aware inference memory estimation of language models.
Author: Sheikyon
License: MIT
Project-URL: Source Code, https://github.com/Sheikyon/LLM-X
Project-URL: Issues, https://github.com/Sheikyon/LLM-X/issues
Classifier: Development Status :: 4 - Beta
Classifier: Intended Audience :: Science/Research
Classifier: License :: OSI Approved :: MIT License
Classifier: Programming Language :: Python :: 3.10
Classifier: Programming Language :: Python :: 3.11
Classifier: Programming Language :: Python :: 3.12
Classifier: Topic :: Scientific/Engineering :: Artificial Intelligence
Requires-Python: >=3.10
License-File: LICENSE
Requires-Dist: typer[all]>=0.12
Requires-Dist: rich>=13
Requires-Dist: httpx>=0.27
Requires-Dist: safetensors>=0.4
Requires-Dist: psutil>=5.9
Requires-Dist: nvidia-ml-py>=12.535.133
Requires-Dist: huggingface-hub>=0.23.0
Dynamic: license-file
